sapdswsdlclient/__init__.py
sapdswsdlclient/exceptions/exceptions.py
sapdswsdlclient/models/batch_job.py
sapdswsdlclient/models/dataflow.py
sapdswsdlclient/models/items.py
sapdswsdlclient/models/job_server.py
sapdswsdlclient/models/logs.py
sapdswsdlclient/models/realtime_service.py
sapdswsdlclient/models/repo.py
sapdswsdlclient/server/__init__.py
sapdswsdlclient/server/auth.py
sapdswsdlclient/server/re_auth.py
sapdswsdlclient/templates/templates.py
sapdswsdlclient-0.1.1.dist-info/licenses/LICENSE.md
sapdswsdlclient-0.1.1.dist-info/METADATA
sapdswsdlclient-0.1.1.dist-info/WHEEL
sapdswsdlclient-0.1.1.dist-info/top_level.txt
sapdswsdlclient-0.1.1.dist-info/RECORD
