Metadata-Version: 2.4
Name: sapdswsdlclient
Version: 0.1.1
Summary: A Python library for SAP Data Services
Home-page: https://github.com/sparklingSky/sap-ds-web-service-client
Author: sparklingSky
License: Custom Dual License
Keywords: SAP,Data Services,SOAP,WSDL
Classifier: Programming Language :: Python :: 3
Classifier: License :: Other/Proprietary License
Classifier: Programming Language :: Python :: 3.12
Requires-Python: >=3.12
License-File: LICENSE.md
Requires-Dist: requests~=2.32.3
Dynamic: author
Dynamic: classifier
Dynamic: description
Dynamic: description-content-type
Dynamic: home-page
Dynamic: keywords
Dynamic: license
Dynamic: license-file
Dynamic: requires-dist
Dynamic: requires-python
Dynamic: summary
